pytest_buildkite/__init__.py
pytest_buildkite-0.3.0.dist-info/LICENSE
pytest_buildkite-0.3.0.dist-info/METADATA
pytest_buildkite-0.3.0.dist-info/WHEEL
pytest_buildkite-0.3.0.dist-info/entry_points.txt
pytest_buildkite-0.3.0.dist-info/top_level.txt
pytest_buildkite-0.3.0.dist-info/RECORD
